house_prices_prediction_pipeline/__init__.py
house_prices_prediction_pipeline/_config.py
house_prices_prediction_pipeline/inference.py
house_prices_prediction_pipeline/preprocess.py
house_prices_prediction_pipeline/train.py
house_prices_prediction_pipeline-0.3.2.3.dist-info/LICENSE
house_prices_prediction_pipeline-0.3.2.3.dist-info/METADATA
house_prices_prediction_pipeline-0.3.2.3.dist-info/WHEEL
house_prices_prediction_pipeline-0.3.2.3.dist-info/top_level.txt
house_prices_prediction_pipeline-0.3.2.3.dist-info/RECORD
