Metadata-Version: 2.1
Name: house-prices-prediction-pipeline
Version: 0.3.2.3
Summary: A package for house price prediction pipeline.
Home-page: https://github.com/saadkhalid-git/house_price_prediction_pipeline
Author: Saad Khalid
Author-email: tosaadkhalid@gmail.com
License: MIT
Platform: UNKNOWN
Requires-Dist: pandas
Requires-Dist: numpy
Requires-Dist: joblib
Requires-Dist: scikit-learn
